signpy-0.2.0.dist-info/METADATA
signpy-0.2.0.dist-info/WHEEL
signpy-0.2.0.dist-info/license_files/LICENSE
signpy/__init__.py
signpy/signpy.cpython-312-darwin.so
signpy-0.2.0.dist-info/RECORD
