Metadata-Version: 2.1
Name: signpy
Version: 0.2.0
Classifier: Programming Language :: Rust
Classifier: Programming Language :: Python :: Implementation :: CPython
Classifier: Programming Language :: Python :: Implementation :: PyPy
Classifier: Topic :: Security :: Cryptography
License-File: LICENSE
Summary: Sign messages with ease
License: MIT
Requires-Python: >=3.8
